AUTHORS
ChangeLog
MANIFEST.in
README.rst
requirements.txt
setup.cfg
setup.py
leonardo_module_vis_temporal/__init__.py
leonardo_module_vis_temporal/models.py
leonardo_module_vis_temporal.egg-info/PKG-INFO
leonardo_module_vis_temporal.egg-info/SOURCES.txt
leonardo_module_vis_temporal.egg-info/dependency_links.txt
leonardo_module_vis_temporal.egg-info/not-zip-safe
leonardo_module_vis_temporal.egg-info/pbr.json
leonardo_module_vis_temporal.egg-info/top_level.txt
leonardo_module_vis_temporal/static/vis/js/analogclock.js
leonardo_module_vis_temporal/static/vis/js/digitalclock.js
leonardo_module_vis_temporal/static/vis/js/polarclock.js
leonardo_module_vis_temporal/static/vis/scss/analogclock.scss
leonardo_module_vis_temporal/static/vis/scss/digitalclock.scss
leonardo_module_vis_temporal/static/vis/scss/polarclock.scss
leonardo_module_vis_temporal/templates/widget/analogclock/_base.html
leonardo_module_vis_temporal/templates/widget/analogclock/braun.html
leonardo_module_vis_temporal/templates/widget/analogclock/default.html
leonardo_module_vis_temporal/templates/widget/analogclock/pf.html
leonardo_module_vis_temporal/templates/widget/analogclock/sbb.html
leonardo_module_vis_temporal/templates/widget/digitalclock/default.html
leonardo_module_vis_temporal/templates/widget/polarclock/default.html
leonardo_module_vis_temporal/templates/widget/polarclock/tick.html
leonardo_module_vis_temporal/widget/__init__.py
leonardo_module_vis_temporal/widget/analogclock/__init__.py
leonardo_module_vis_temporal/widget/analogclock/models.py
leonardo_module_vis_temporal/widget/digitalclock/__init__.py
leonardo_module_vis_temporal/widget/digitalclock/models.py
leonardo_module_vis_temporal/widget/polarclock/__init__.py
leonardo_module_vis_temporal/widget/polarclock/models.py